{
    "GaussianBlob": {
        "ic": {
            "_gamma": 0.5,
            "contamination": 0.1,
            "n_neighbors": 10,
            "affinity": "rbf",
            "tpr": 1.0,
            "tnr": 1.0
        },
        "lof": {
            "_gamma": 0.1,
            "contamination": 0.15,
            "n_neighbors": 20,
            "affinity": "rbf",
            "tpr": 1.0,
            "tnr": 1.0
        },
        "if": {
            "_gamma": 0.1,
            "contamination": 0.15,
            "n_neighbors": 10,
            "affinity": "rbf",
            "tpr": 1.0,
            "tnr": 1.0
        },
        "ee": {
            "_gamma": 0.1,
            "contamination": 0.15,
            "n_neighbors": 10,
            "affinity": "rbf",
            "tpr": 1.0,
            "tnr": 1.0
        },
        "svm": {
            "_gamma": 0.1,
            "contamination": 0.15,
            "n_neighbors": 10,
            "affinity": "rbf",
            "tpr": 0.9882352941176471,
            "tnr": 0.9111111111111111
        }
    },
    "Moon": {
        "ic": {
            "_gamma": 0.41,
            "contamination": 0.05,
            "n_neighbors": 50,
            "affinity": [
                "rbf",
                "nearest_neighbors"
            ],
            "tpr": 0.97,
            "tnr": 0.7111111111111111
        },
        "lof": {
            "_gamma": 0.1,
            "contamination": 0.13,
            "n_neighbors": 10,
            "affinity": "rbf",
            "tpr": 1.0,
            "tnr": 1.0
        },
        "if": {
            "_gamma": 0.1,
            "contamination": 0.13,
            "n_neighbors": 10,
            "affinity": "rbf",
            "tpr": 0.9666666666666667,
            "tnr": 0.7777777777777778
        },
        "ee": {
            "_gamma": 0.1,
            "contamination": 0.13,
            "n_neighbors": 10,
            "affinity": "rbf",
            "tpr": 0.9133333333333333,
            "tnr": 0.4222222222222222
        },
        "svm": {
            "_gamma": 0.1,
            "contamination": 0.13,
            "n_neighbors": 10,
            "affinity": "rbf",
            "tpr": 0.93,
            "tnr": 0.5555555555555556
        }
    },
    "Lymphography": {
        "ic": {
            "_gamma": 0.1,
            "contamination": 0.1,
            "n_neighbors": 60,
            "affinity": "laplacian",
            "tpr": 0.9788732394366197,
            "tnr": 1.0
        },
        "lof": {
            "_gamma": 0.1,
            "contamination": 0.041,
            "n_neighbors": 60,
            "affinity": "rbf",
            "tpr": 0.9859154929577465,
            "tnr": 0.8333333333333334
        },
        "if": {
            "_gamma": 0.1,
            "contamination": 0.041,
            "n_neighbors": 10,
            "affinity": "rbf",
            "tpr": 0.9929577464788732,
            "tnr": 1.0
        },
        "ee": {
            "_gamma": 0.1,
            "contamination": 0.1,
            "n_neighbors": 10,
            "affinity": "rbf",
            "tpr": 0.9366197183098591,
            "tnr": 1.0
        },
        "svm": {
            "_gamma": 0.1,
            "contamination": 0.1,
            "n_neighbors": 10,
            "affinity": "rbf",
            "tpr": 0.9295774647887324,
            "tnr": 0.6666666666666666
        }
    },
    "Glass": {
        "ic": {
            "_gamma": 0.05,
            "contamination": 0.05,
            "n_neighbors": 190,
            "affinity": "rbf",
            "tpr": 0.9121951219512195,
            "tnr": 0.1111111111111111
        },
        "lof": {
            "_gamma": 0.1,
            "contamination": 0.041,
            "n_neighbors": 2,
            "affinity": "rbf",
            "tpr": 0.9658536585365853,
            "tnr": 0.2222222222222222
        },
        "if": {
            "_gamma": 0.1,
            "contamination": 0.1,
            "n_neighbors": 10,
            "affinity": "rbf",
            "tpr": 0.9024390243902439,
            "tnr": 0.2222222222222222
        },
        "ee": {
            "_gamma": 0.1,
            "contamination": 0.05,
            "n_neighbors": 10,
            "affinity": "rbf",
            "tpr": 0.9463414634146341,
            "tnr": 0.0
        },
        "svm": {
            "_gamma": 0.1,
            "contamination": 0.1,
            "n_neighbors": 10,
            "affinity": "rbf",
            "tpr": 0.9170731707317074,
            "tnr": 0.2222222222222222
        }
    },
    "Ionosphere": {
        "ic": {
            "_gamma": 0.29,
            "contamination": 0.359,
            "n_neighbors": 50,
            "affinity": "rbf",
            "tpr": 0.9066666666666666,
            "tnr": 0.48412698412698413
        },
        "lof": {
            "_gamma": 0.047,
            "contamination": 0.359,
            "n_neighbors": 9,
            "affinity": [
                "rbf",
                "nearest_neighbors",
                "reweight"
            ],
            "tpr": 0.9022222222222223,
            "tnr": 0.8253968253968254
        },
        "if": {
            "_gamma": 0.29,
            "contamination": 0.359,
            "n_neighbors": 290,
            "affinity": [
                "rbf",
                "nearest_neighbors"
            ],
            "tpr": 0.8044444444444444,
            "tnr": 0.6507936507936508
        },
        "ee": {
            "_gamma": 0.29,
            "contamination": 0.359,
            "n_neighbors": 290,
            "affinity": [
                "rbf",
                "nearest_neighbors"
            ],
            "tpr": 0.9333333333333333,
            "tnr": 0.8809523809523809
        },
        "svm": {
            "_gamma": 0.4,
            "contamination": 0.359,
            "n_neighbors": 290,
            "affinity": "rbf",
            "tpr": 0.8311111111111111,
            "tnr": 0.6904761904761905
        }
    }
}